eagle/__init__.py
eagle/agents/__init__.py
eagle/agents/agent_memory/__init__.py
eagle/agents/agent_memory/agent_memory_templates/__init__.py
eagle/agents/agent_memory/agent_memory_templates/conversation_basic.py
eagle/agents/agent_memory/base.py
eagle/agents/agent_memory/conversation_memory/__init__.py
eagle/agents/agent_memory/conversation_memory/simple_conversation_memory.py
eagle/agents/agent_memory/observation_memory/__init__.py
eagle/agents/agent_memory/observation_memory/simple_observation_memory.py
eagle/agents/agent_memory/planning_memory/__init__.py
eagle/agents/agent_memory/planning_memory/todo_list_planning_memory.py
eagle/agents/agent_memory/shared_memory/__init__.py
eagle/agents/agent_memory/shared_memory/shared_objects_memory.py
eagle/agents/agent_models/__init__.py
eagle/agents/agent_models/react_agent.py
eagle/agents/base.py
eagle/agents/cognitive_models/__init__.py
eagle/agents/cognitive_models/base.py
eagle/agents/cognitive_models/react/__init__.py
eagle/agents/cognitive_models/react/prompts.py
eagle/agents/cognitive_models/react/react_model.py
eagle/agents/react_agent/__init__.py
eagle/agents/react_agent/base.py
eagle/agents/react_agent/prompts.py
eagle/agents/specialists/__init__.py
eagle/agents/specialists/coding/__init__.py
eagle/agents/specialists/coding/base.py
eagle/agents/specialists/coding/prompts.py
eagle/agents/specialists/data_analysis/__init__.py
eagle/agents/specialists/data_analysis/dataframe_rows_analyst/__init__.py
eagle/agents/specialists/data_analysis/dataframe_rows_analyst/base.py
eagle/agents/specialists/data_analysis/dataframe_rows_analyst/prompts.py
eagle/agents/specialists/planning/__init__.py
eagle/agents/specialists/planning/base.py
eagle/chains/coding_objects_handling.py
eagle/chains/coding_problems_chain.py
eagle/chains/image_interpretation.py
eagle/chains/plan_evaluation.py
eagle/chains/plan_processing.py
eagle/chains/plan_qa.py
eagle/chains/plan_qa_construction.py
eagle/chains/self_rag_chains.py
dev_tools_eagle_test-0.6.1.dist-info/METADATA
dev_tools_eagle_test-0.6.1.dist-info/WHEEL
dev_tools_eagle_test-0.6.1.dist-info/RECORD
