Metadata-Version: 2.1
Name: dev-tools-eagle-test
Version: 0.6.1
Summary: Implements LangGraph based agents following the CoALA framework.
Author: Pedro Henrique Thompson Furtado
Author-email: pedrothompson@petrobras.com.br
Requires-Python: >=3.10,<3.14
Classifier: Programming Language :: Python :: 3
Classifier: Programming Language :: Python :: 3.10
Classifier: Programming Language :: Python :: 3.11
Classifier: Programming Language :: Python :: 3.12
Classifier: Programming Language :: Python :: 3.13
Requires-Dist: SQLAlchemy (>=1.4,<2.0.42)
Requires-Dist: aiohttp (>=3.8.3,<3.12.7)
Requires-Dist: arxiv (>=2.1.3)
Requires-Dist: async-timeout (>=4.0.0,<5.0.0)
Requires-Dist: curl-cffi (>=0.10.0)
Requires-Dist: dash (>=3.2.0,<4.0.0)
Requires-Dist: dash-bootstrap-components (>=2.0.4,<3.0.0)
Requires-Dist: dash-html-components (>=2.0.0,<3.0.0)
Requires-Dist: duckduckgo-search (>=8.0.1)
Requires-Dist: fastparquet (>=2024.5.0)
Requires-Dist: filelock (>=3.17.0)
Requires-Dist: func-timeout (>=4.3.5)
Requires-Dist: ipywidgets (>=8.1.3)
Requires-Dist: jinja2 (>=3.1.5)
Requires-Dist: json-repair (>=0.52.3,<0.53.0)
Requires-Dist: jupyter-contrib-nbextensions (>=0.7.0)
Requires-Dist: jupyterlab (>=4.4.2)
Requires-Dist: kaleido (>=1.1.0,<2.0.0)
Requires-Dist: langchain (<=0.3.27)
Requires-Dist: langchain-community (<=0.3.31)
Requires-Dist: langchain-core (<=0.3.79)
Requires-Dist: langchain-experimental (<0.4.0)
Requires-Dist: langchain-openai (<=0.3.35)
Requires-Dist: langgraph (<=0.6.11)
Requires-Dist: langsmith
Requires-Dist: lark (>=1.1.9)
Requires-Dist: matplotlib (>=3.10.0)
Requires-Dist: neo4j (>=6.0.2,<7.0.0)
Requires-Dist: networkx (>=3.4.2)
Requires-Dist: numpy (>1.26.4,<2.2.6)
Requires-Dist: openpyxl (>=3.1.4)
Requires-Dist: opensearch-py (>=2.7.1,<4.0.0)
Requires-Dist: osisoft-pidevclub-piwebapi-thompsonp17 (>=1.2.0)
Requires-Dist: pandas (<2.3.0)
Requires-Dist: pdf2image (>=1.17.0,<2.0.0)
Requires-Dist: plotly (>=6.0.0)
Requires-Dist: poppler-utils (>=0.1.0,<0.2.0)
Requires-Dist: pyarrow (>=16.1.0)
Requires-Dist: pydantic (>=2.10.6)
Requires-Dist: pypdf (>=6.0.0,<7.0.0)
Requires-Dist: python-dotenv (>=1.0.1)
Requires-Dist: python-levenshtein (>=0.25.1)
Requires-Dist: pyvis (>=0.3.2)
Requires-Dist: requests (>=2.32.3)
Requires-Dist: restrictedpython (>=7.0)
Requires-Dist: scikit-learn (>=1.5.0)
Requires-Dist: tabulate (>=0.9.0)
Requires-Dist: tenacity (>=8.4.0,<9.0.0)
Requires-Dist: xlrd (>=2.0.1)
Requires-Dist: yfinance (>=0.2.59)
